asc.cpython-39-darwin.so
anyks_sc-1.2.6.data/data/include/alm/ablm.hpp
anyks_sc-1.2.6.data/data/include/alm/alm.hpp
anyks_sc-1.2.6.data/data/include/alm/alphabet.hpp
anyks_sc-1.2.6.data/data/include/alm/alt.hpp
anyks_sc-1.2.6.data/data/include/alm/arpa.hpp
anyks_sc-1.2.6.data/data/include/alm/ascb.hpp
anyks_sc-1.2.6.data/data/include/alm/aspl.hpp
anyks_sc-1.2.6.data/data/include/alm/bloom.hpp
anyks_sc-1.2.6.data/data/include/alm/collector.hpp
anyks_sc-1.2.6.data/data/include/alm/dict.hpp
anyks_sc-1.2.6.data/data/include/alm/dumper.hpp
anyks_sc-1.2.6.data/data/include/alm/env.hpp
anyks_sc-1.2.6.data/data/include/alm/fsys.hpp
anyks_sc-1.2.6.data/data/include/alm/hnsw.hpp
anyks_sc-1.2.6.data/data/include/alm/idw.hpp
anyks_sc-1.2.6.data/data/include/alm/levenshtein.hpp
anyks_sc-1.2.6.data/data/include/alm/nwt.hpp
anyks_sc-1.2.6.data/data/include/alm/progress.hpp
anyks_sc-1.2.6.data/data/include/alm/python.hpp
anyks_sc-1.2.6.data/data/include/alm/spl.hpp
anyks_sc-1.2.6.data/data/include/alm/stemmer.hpp
anyks_sc-1.2.6.data/data/include/alm/threadpool.hpp
anyks_sc-1.2.6.data/data/include/alm/tokenizer.hpp
anyks_sc-1.2.6.data/data/include/alm/toolkit.hpp
anyks_sc-1.2.6.data/data/include/alm/word.hpp
anyks_sc-1.2.6.data/data/include/alm/app/alm.hpp
anyks_sc-1.2.6.data/data/include/asc/ablm.hpp
anyks_sc-1.2.6.data/data/include/asc/alm.hpp
anyks_sc-1.2.6.data/data/include/asc/alphabet.hpp
anyks_sc-1.2.6.data/data/include/asc/alt.hpp
anyks_sc-1.2.6.data/data/include/asc/arpa.hpp
anyks_sc-1.2.6.data/data/include/asc/ascb.hpp
anyks_sc-1.2.6.data/data/include/asc/aspl.hpp
anyks_sc-1.2.6.data/data/include/asc/bloom.hpp
anyks_sc-1.2.6.data/data/include/asc/collector.hpp
anyks_sc-1.2.6.data/data/include/asc/dict.hpp
anyks_sc-1.2.6.data/data/include/asc/dumper.hpp
anyks_sc-1.2.6.data/data/include/asc/env.hpp
anyks_sc-1.2.6.data/data/include/asc/fsys.hpp
anyks_sc-1.2.6.data/data/include/asc/hnsw.hpp
anyks_sc-1.2.6.data/data/include/asc/idw.hpp
anyks_sc-1.2.6.dist-info/LICENSE
anyks_sc-1.2.6.dist-info/METADATA
anyks_sc-1.2.6.dist-info/WHEEL
anyks_sc-1.2.6.dist-info/top_level.txt
anyks_sc-1.2.6.dist-info/RECORD
