Metadata-Version: 2.1
Name: anyks-sc
Version: 1.2.6
Summary: Smart language model
Home-page: https://github.com/anyks/asc
Download-URL: https://github.com/anyks/asc/archive/release.tar.gz
Author: Yuriy Lobarev
Author-email: forman@anyks.com
Keywords: nlp,lm,alm,language-model,spellchecker,spell-checker,anyks
Classifier: Programming Language :: Python :: 3
Classifier: License :: OSI Approved :: MIT License
Classifier: Operating System :: MacOS
Classifier: Operating System :: POSIX :: Linux
Classifier: Operating System :: POSIX :: BSD :: FreeBSD
Requires: pybind11
Requires-Python: >=3.6
License-File: LICENSE
